{"5": [{"page": "Home", "function": [{"function": "Welcome Message", "parameter": [{"name": "test_url", "answer": "http://localhost:8000/"}]}, {"function": "Introduction to Converter", "parameter": [{"name": "test_url", "answer": "http://localhost:8000/"}, {"name": "introduction_id", "answer": "html-output-id"}]}, {"function": "Navigation Links", "parameter": [{"name": "test_url", "answer": "http://localhost:8000/"}, {"name": "convert_link_id", "answer": "convert-button"}, {"name": "expected_url", "answer": ""}]}]}, {"page": "Convert", "function": [{"function": "Markdown Input Area", "parameter": [{"name": "test_url", "answer": "http://localhost:8000/convert-markdown-to-html"}, {"name": "markdown_input_id", "answer": "markdown-input"}]}, {"function": "Convert Button", "parameter": [{"name": "convert_button_id", "answer": "convert-button"}]}, {"function": "HTML Output Area", "parameter": [{"name": "html_output_id", "answer": "html-output-id"}]}, {"function": "Rule Check 1", "parameter": [{"name": "html_output_id", "answer": "html-output-id"}]}, {"function": "Upload File", "parameter": [{"name": "test_url", "answer": "http://localhost:8000/convert-markdown-to-html"}, {"name": "upload_file_id", "answer": ""}, {"name": "upload_file_btn_id", "answer": ""}]}, {"function": "Download HTML", "parameter": [{"name": "download_html_btn_id", "answer": ""}, {"name": "default_download_path", "answer": ""}]}, {"function": "Rule Check 2", "parameter": [{"name": "default_download_path", "answer": ""}]}]}, {"page": "About", "function": [{"function": "Team Information", "parameter": [{"name": "test_url", "answer": "http://localhost:8000/about"}]}, {"function": "FAQ Section", "parameter": [{"name": "test_url", "answer": "http://localhost:8000/about"}]}]}], "7": [{"page": "Home", "function": [{"function": "Navigate to Dashboards", "parameter": []}, {"function": "Access Settings", "parameter": []}, {"function": "Open About", "parameter": []}]}, {"page": "Dashboards", "function": [{"function": "View Balance Status", "parameter": []}, {"function": "Analyze Trends", "parameter": []}, {"function": "Examine Categories", "parameter": []}]}, {"page": "Balance", "function": [{"function": "Add Transaction", "parameter": []}, {"function": "Delete Transaction", "parameter": []}, {"function": "Edit Transaction Details", "parameter": []}]}, {"page": "Reports", "function": [{"function": "Generate Monthly Report", "parameter": []}, {"function": "Export Data", "parameter": []}]}, {"page": "Settings", "function": [{"function": "Update Profile", "parameter": []}]}, {"page": "About", "function": [{"function": "View Support Information", "parameter": []}]}, {"page": "Sign up", "function": [{"function": "SignupNewUser", "parameter": []}, {"function": "Verify New User", "parameter": []}, {"function": "Edit Sign Up Details", "parameter": []}]}, {"page": "Sign in", "function": [{"function": "LoginUser", "parameter": []}]}, {"page": "Account", "function": [{"function": "View Account Balance", "parameter": []}, {"function": "Edit User Preferences", "parameter": []}]}, {"page": "Help", "function": [{"function": "Search Help Topics", "parameter": []}, {"function": "Contact Support", "parameter": []}]}, {"page": "Home", "function": [{"function": "Navigate to Dashboards", "parameter": []}, {"function": "Access Settings", "parameter": []}, {"function": "Open About", "parameter": []}]}, {"page": "Dashboards", "function": [{"function": "View Balance Status", "parameter": []}, {"function": "Analyze Trends", "parameter": []}, {"function": "Examine Categories", "parameter": []}]}, {"page": "Balance", "function": [{"function": "Add Transaction", "parameter": []}, {"function": "Delete Transaction", "parameter": []}, {"function": "Edit Transaction Details", "parameter": []}]}, {"page": "Reports", "function": [{"function": "Generate Monthly Report", "parameter": [{"name": "test_url", "answer": "http://localhost:8000/reports/"}]}, {"function": "Export Data", "parameter": [{"name": "test_url", "answer": "http://localhost:8000/reports/"}, {"name": "default_download_path", "answer": "/home/user/"}]}]}, {"page": "Settings", "function": [{"function": "Update Profile", "parameter": [{"name": "test_url", "answer": "http://localhost:8000/settings/update_profile"}]}]}, {"page": "About", "function": [{"function": "View Support Information", "parameter": []}]}, {"page": "Sign up", "function": [{"function": "SignupNewUser", "parameter": [{"name": "test_url", "answer": "http://localhost:8000/signup"}]}, {"function": "Verify New User", "parameter": []}, {"function": "Edit Sign Up Details", "parameter": []}]}, {"page": "Sign in", "function": [{"function": "LoginUser", "parameter": [{"name": "test_url", "answer": "http://localhost:8000/signin"}]}]}, {"page": "Account", "function": [{"function": "View Account Balance", "parameter": []}, {"function": "Edit User Preferences", "parameter": []}]}, {"page": "Help", "function": [{"function": "Search Help Topics", "parameter": []}, {"function": "Contact Support", "parameter": []}]}], "15": [{"page": "Home", "function": [{"function": "Button to 'HelloWorld' page", "parameter": [{"name": "test_url", "answer": "http://localhost:8000/helloworld/"}]}]}, {"page": "HelloWorld", "function": [{"function": "Display 'HelloWorld' message", "parameter": []}]}], "18": [{"page": "Main Menu", "function": [{"function": "Welcome Message", "parameter": [{"name": "expected_output", "answer": "Welcome to the Adventure Game! Choose an option: 1. Start Game 2. Help"}]}, {"function": "Help in Main Menu", "parameter": [{"name": "help_in_main_menu_command", "answer": "2"}, {"name": "expected_output", "answer": "Choose an option: 1. Start Game 2. Help\n1. Start Game: Begins your adventure.\n2. Help: Displays this help information."}]}, {"function": "Wrong Selection Check", "parameter": [{"name": "expected_output", "answer": "Invalid selection. Please choose a valid option."}]}, {"function": "Start Game", "parameter": [{"name": "start_game_command", "answer": "1"}, {"name": "expected_output", "answer": "You are now starting the game! You find yourself in a room with exits to the north and south."}]}]}, {"page": "Game", "function": [{"function": "Display Help", "parameter": [{"name": "help_in_game", "answer": "help"}, {"name": "expected_output", "answer": "Available commands: go [direction], look, inventory, pick up [item]"}]}, {"function": "Look Around", "parameter": [{"name": "expected_output", "answer": "You are in a small room. There is an exit to the north and south."}]}, {"function": "Move Player", "parameter": [{"name": "direction", "answer": "north"}, {"name": "expected_output", "answer": "You move north and enter a forest clearing with pathways leading east and west."}]}, {"function": "Move Back", "parameter": [{"name": "expected_output", "answer": "You move south and return to the initial room."}]}, {"function": "Check Inventory 1", "parameter": [{"name": "check_inventory_command", "answer": "inventory"}, {"name": "expected_output", "answer": "You are carrying nothing."}]}, {"function": "Pick Item", "parameter": [{"name": "directions", "answer": "north,west"}, {"name": "expected_output", "answer": "You pick up a magic stone in the west path of the forest clearing."}]}, {"function": "Check Inventory 2", "parameter": [{"name": "check_inventory_command", "answer": "inventory"}, {"name": "expected_output", "answer": "You are carrying a magic stone."}]}, {"function": "Win the Game", "parameter": [{"name": "directions", "answer": "south,south,north,use_stone"}, {"name": "expected_output", "answer": "Congratulations! You used the magic stone to unlock the secret passage and complete your adventure."}]}]}, {"page": "Main Menu 2", "function": [{"function": "Exit Game", "parameter": [{"name": "exit_command", "answer": "quit"}, {"name": "expected_output", "answer": "Thank you for playing! See you next time."}]}]}]}