{"2": "```json\n{\n\"page\": \"Home Page\",\n\"function\": [\n{\n\"function\": \"Select Source Currency\",\n\"parameter\": [\n{\n\"name\": \"test_url\",\n\"answer\": \"http://localhost:8000/\"\n},\n{\n\"name\": \"source_currency_dropdown_id\",\n\"answer\": \"your_dropdown_id\"\n},\n{\n\"name\": \"source_currency_value\",\n\"answer\": \"USD\"\n}\n],\n...\n}\n...\n```", "4": "```json\n{\n\"page\": \"Home\",\n\"function\": [\n{\n\"function\": \"Introduction\",\n\"parameter\": [\n{\n\"name\": \"test_url\",\n\"answer\": \"http://localhost:8000/\"\n},\n{\n\"name\": \"intro_text_css_selector\",\n\"answer\": \"#intro-text\"\n}\n]\n},\n...\n]\n},\n...\n}\n```", "10": "```json\n[\n  {\n    \"page\": \"Home\",\n    \"function\": [\n      {\n        \"function\": \"View Latest Posts\",\n        \"parameter\": []\n      },\n      {\n        \"function\": \"Trending Topics\",\n        \"parameter\": []\n      }\n    ]\n  },\n  ...\n]\n```", "12": "```json\n{\n\"page\": \"Main Page\",\n\"function\": [\n{\n\"function\": \"Search and Filter Data\",\n\"parameter\": [\n{\n\"name\": \"search_term\",\n\"answer\": \"your_search_term\"\n},\n{\n\"name\": \"filter_criteria\",\n\"answer\": \"your_filter_criteria\"\n}\n],\n...\n}\n```", "15": {"Home": [{"function": [{"function": "Button to 'HelloWorld' page", "parameter": [{"name": "test_url", "answer": "example_project.urls.home"}]}]}], "HelloWorld": [{"function": [{"function": "Display 'HelloWorld' message", "parameter": []}]}]}, "16": "```json\n{\n  \"page\": \"Input File Validation\",\n  \"function\": [\n    {\n      \"function\": \"CheckFileExistence\",\n      \"parameter\": [\n        {\n          \"name\": \"entry\",\n          \"answer\": \"16-stdanswer.py\"\n        },\n        {\n          \"name\": \"error_message\",\n          \"answer\": \"File does not exist.\"\n        }\n      ]\n    },\n    {\n      \"function\": \"ValidateHeaders\",\n      \"parameter\": [\n        {\n          \"name\": \"entry\",\n          \"answer\": \"16-stdanswer.py\"\n        },\n        {\n          \"name\": \"error_message\",\n          \"answer\": \"Incorrect table headers.\"\n        }\n      ]\n    },\n    {\n      \"function\": \"ValidateNullValue\",\n      \"parameter\": [\n        {\n          \"name\": \"entry\",\n          \"answer\": \"16-stdanswer.py\"\n        },\n        {\n          \"name\": \"error_message\",\n          \"answer\": \"Missing values in the table.\"\n        }\n      ]\n    },\n    {\n      \"function\": \"ValidateTimeColumn\",\n      \"parameter\": [\n        {\n          \"name\": \"entry\",\n          \"answer\": \"16-stdanswer.py\"\n        },\n        {\n          \"name\": \"error_message\",\n          \"answer\": \"Time column values are not valid.\"\n        }\n      ]\n    },\n    {\n      \"function\": \"ValidateDataIntegrity\",\n      \"parameter\": [\n        {\n          \"name\": \"entry\",\n          \"answer\": \"16-stdanswer.py\"\n        },\n        {\n          \"name\": \"error_message\",\n          \"answer\": \"Data integrity issues in the Weekday column.\"\n        }\n      ]\n    }\n  ]\n},\n{\n  \"page\": \"Data Transformation and File Output\",\n  \"function\": [\n    {\n      \"function\": \"EmptyFileRun\",\n      \"parameter\": [\n        {\n          \"name\": \"entry\",\n          \"answer\": \"16-stdanswer.py\"\n        }\n      ]\n    },\n    {\n      \"function\": \"RunProject\",\n      \"parameter\": [\n        {\n          \"name\": \"entry\",\n          \"answer\": \"16-stdanswer.py\"\n        }\n      ]\n    },\n    {\n      \"function\": \"OutputFileCheck\",\n      \"parameter\": []\n    }\n  ]\n}\n```"}