{"2": "{\"page\": \"Home Page\", \"function\": [{\"function\": \"Select Source Currency\", \"parameter\": [{\"name\": \"test_url\", \"answer\": \"http://localhost:8000/\"}, {\"name\": \"source_currency_dropdown_id\", \"answer\": \"fromCurrency\"}, {\"name\": \"source_currency_value\", \"answer\": \"USD\"}]}, {\"function\": \"Select Target Currency\", \"parameter\": [{\"name\": \"test_url\", \"answer\": \"http://localhost:8000/\"}, {\"name\": \"target_currency_dropdown_id\", \"answer\": \"toCurrency\"}, {\"name\": \"target_currency_value\", \"answer\": \"EUR\"}]}, {\"function\": \"Enter Amount\", \"parameter\": [{\"name\": \"test_url\", \"answer\": \"http://localhost:8000/\"}, {\"name\": \"amount_input_box_id\", \"answer\": \"amount\"}, {\"name\": \"amount_value\", \"answer\": \"100\"}]}, {\"function\": \"Convert Button\", \"parameter\": [{\"name\": \"convert_button_id\", \"answer\": \"currency-converter-form\"}]}, {\"function\": \"Display Conversion Result\", \"parameter\": [{\"name\": \"test_url\", \"answer\": \"http://localhost:8000/\"}, {\"name\": \"result_box_id\", \"answer\": \"\"}]}, {\"function\": \"Exchange Rate Info\", \"parameter\": [{\"name\": \"test_url\", \"answer\": \"http://localhost:8000/\"}, {\"name\": \"exchange_rate_info_id\", \"answer\": \"\"}]}]}, {\"page\": \"Currency Details Page\", \"function\": [{\"function\": \"Currency Information\", \"parameter\": [{\"name\": \"test_url\", \"answer\": \"http://localhost:8000/\"}, {\"name\": \"currency_info_id\", \"answer\": \"\"}]}, {\"function\": \"Historical Exchange Rates\", \"parameter\": [{\"name\": \"test_url\", \"answer\": \"http://localhost:8000/\"}, {\"name\": \"historical_rates_id\", \"answer\": \"\"}]}]}} \n\n\n", "4": [{"page": "Home", "function": [{"function": "Introduction", "parameter": [{"name": "test_url", "answer": "http://localhost:8000/"}, {"name": "intro_text_css_selector", "answer": "h1"}]}, {"function": "Generate QR Code Navigate Button", "parameter": [{"name": "test_url", "answer": "http://localhost:8000/"}, {"name": "generate_qr_button_id", "answer": "none"}, {"name": "expected_url", "answer": "http://localhost:8000/generate-qr-code/"}, {"name": "generator_id", "answer": "none"}]}]}, {"page": "QR Code Generator", "function": [{"function": "Text Input Field", "parameter": [{"name": "test_url", "answer": "http://localhost:8000/generate-qr-code/"}, {"name": "text_input_id", "answer": "data-input"}]}, {"function": "Enter Box Size", "parameter": [{"name": "box_size_input_id", "answer": "none"}]}, {"function": "Enter Border Size", "parameter": [{"name": "border_size_input_id", "answer": "none"}]}, {"function": "Select Fill Color", "parameter": [{"name": "fill_color_select_id", "answer": "none"}]}, {"function": "Select Back Color", "parameter": [{"name": "back_color_select_id", "answer": "none"}]}, {"function": "Select Error Correction Rate", "parameter": [{"name": "correction_rate_select_id", "answer": "none"}]}, {"function": "Generate Button", "parameter": [{"name": "generate_button_id", "answer": "none"}]}, {"function": "QR Code Display Area", "parameter": [{"name": "qr_code_display_id", "answer": "qr-code-container"}]}, {"function": "Download QR Code Button", "parameter": [{"name": "test_url", "answer": "http://localhost:8000/generate-qr-code/"}, {"name": "default_download_path", "answer": "C:\\Users\\YourUserName\\Downloads"}]}, {"function": "Error Handling", "parameter": [{"name": "test_url", "answer": "http://localhost:8000/generate-qr-code/"}, {"name": "text_input_id", "answer": "data-input"}, {"name": "generate_button_id", "answer": "none"}, {"name": "error_message_css_selector", "answer": "error-message"}]}]}, {"page": "About", "function": [{"function": "Description", "parameter": [{"name": "test_url", "answer": "http://localhost:8000/about/"}, {"name": "about_description_css_selector", "answer": "p.about-text"}]}, {"function": "Common Questions", "parameter": [{"name": "test_url", "answer": "http://localhost:8000/about/"}, {"name": "faq_id", "answer": "none"}]}, {"function": "Privacy Policy", "parameter": [{"name": "test_url", "answer": "http://localhost:8000/about/"}, {"name": "privacy_policy_id", "answer": "none"}]}, {"function": "Terms of Service", "parameter": [{"name": "test_url", "answer": "http://localhost:8000/about/"}, {"name": "terms_of_service_id", "answer": "none"}]}]}], "5": [{"page": "Home", "function": [{"function": "Welcome Message", "parameter": [{"name": "test_url", "answer": "http://localhost:8000/"}]}, {"function": "Introduction to Converter", "parameter": [{"name": "test_url", "answer": "http://localhost:8000/"}, {"name": "introduction_id", "answer": "intro-converter"}]}, {"function": "Navigation Links", "parameter": [{"name": "test_url", "answer": "http://localhost:8000/"}, {"name": "convert_link_id", "answer": "convert-link"}, {"name": "expected_url", "answer": "http://localhost:8000/convert"}]}]}, {"page": "Convert", "function": [{"function": "Markdown Input Area", "parameter": [{"name": "test_url", "answer": "http://localhost:8000/convert"}, {"name": "markdown_input_id", "answer": "markdown-input"}]}, {"function": "Convert Button", "parameter": [{"name": "convert_button_id", "answer": "convert-btn"}]}, {"function": "HTML Output Area", "parameter": [{"name": "html_output_id", "answer": "html-output"}]}, {"function": "Upload File", "parameter": [{"name": "test_url", "answer": "http://localhost:8000/convert"}, {"name": "upload_file_id", "answer": "file-input"}, {"name": "upload_file_btn_id", "answer": "upload-btn"}]}, {"function": "Download HTML", "parameter": [{"name": "download_html_btn_id", "answer": "download-btn"}, {"name": "default_download_path", "answer": "./converted_html.html"}]}]}, {"page": "About", "function": [{"function": "Team Information", "parameter": [{"name": "test_url", "answer": "http://localhost:8000/about"}]}, {"function": "FAQ Section", "parameter": [{"name": "test_url", "answer": "http://localhost:8000/about"}]}]}], "6": "[{\"page\":\"Home\", \"function\":[{\"function\":\"View Dashboard\", \"parameter\": [{\"name\":\"test_url\", \"answer\":\"http://localhost:8000/\"}, {\"name\":\"navigate_dashboard_id\", \"answer\":\"dashboard-link\"}]}, {\"function\":\"Navigate to Todo Lists\", \"parameter\": [{\"name\":\"test_url\", \"answer\":\"http://localhost:8000/todolists/\"}, {\"name\":\"navigate_todo_lists_id\", \"answer\":\"TodoListsButton\"}]}]}, {\"page\":\"Todo List\", \"function\":[{\"function\":\"Create New List\", \"parameter\": [{\"name\":\"test_url\", \"answer\":\"http://localhost:8000/newlist/\"}, {\"name\":\"add_button_id\", \"answer\":\"addButton\"}, {\"name\":\"list_input_box_id\", \"answer\":\"newListInput\"}]}, {\"function\":\"View Task 2\", \"parameter\": [{\"name\":\"test_url\", \"answer\":\"http://localhost:8000/task/\"}, {\"name\":\"task_class\", \"answer\":\"taskItem\"}]}, {\"function\":\"Mark Task as Completed 2\", \"parameter\": [{\"name\":\"complete_button_class\", \"answer\":\"completedButton\"}]}]}, {\"page\":\"Analysis\", \"function\":[{\"function\":\"Return to Todolists\", \"parameter\": [{\"name\":\"return_link_id\", \"answer\":\"ToDoListLink\"}]}, {\"function\":\"Return to Homepage\", \"parameter\": [{\"name\":\"return_link_id\", \"answer\":\"HomePageLink\"}]}]}, {\"page\":\"Todo List 2\", \"function\":[{\"function\":\"Edit List\", \"parameter\": [{\"name\":\"test_url\", \"answer\":\"http://localhost:8000/editlist/\"}, {\"name\":\"edit_button_xpath\", \"answer\":\"//button[contains(text(), 'Edit')]\"},  {\"name\":\"list_input_box_id\", \"answer\":\"EditedListInput\"}]}, {\"function\":\"Delete List\", \"parameter\": [{\"name\":\"test_url\", \"answer\":\"http://localhost:8000/deletelist/\"}, {\"name\":\"delete_button_xpath\", \"answer\":\"//button[contains(text(), 'Delete')]\"}, ]}]\n]", "13": "[{\"page\":\"Home\", \"function\":[{\"function\":\"Login User\", \"parameter\": [{\"name\":\"email\", \"answer\": \"\"}, {\"name\":\"password\", \"answer\": \"\"}]}, {\"function\":\"Register User\", \"parameter\": [{\"name\":\"username\", \"answer\": \"\"}, {\"name\":\"email\", \"answer\": \"\"}, {\"name\":\"password\", \"answer\": \"\"}, {\"name\":\"confirm_password\", \"answer\": \"\"}]}]}, {\"page\":\"Customer Management\", \"function\":[{\"function\":\"View All Customers\", \"parameter\":[]}, {\"function\":\"Add New Customer\", \"parameter\": [{\"name\":\"full_name\", \"answer\": \"\"}, {\"name\":\"email\", \"answer\": \"\"}, {\"name\":\"phone\", \"answer\": \"\"}, {\"name\":\"address\", \"answer\": \"\"}]}, {\"function\":\"Edit Customer Details\", \"parameter\": [{\"name\":\"customer_id\", \"answer\": \"\"}, {\"name\":\"full_name\", \"answer\": \"\"}, {\"name\":\"email\", \"answer\": \"\"}, {\"name\":\"phone\", \"answer\": \"\"}, {\"name\":\"address\", \"answer\": \"\"}]}, {\"function\":\"Delete Customer\", \"parameter\": [{\"name\":\"customer_id\", \"answer\": \"\"}]}]}, {\"page\":\"Product Management\", \"function\":[{\"function\":\"View All Products\", \"parameter\":[]}, {\"function\":\"Add New Product\", \"parameter\": [{\"name\":\"product_name\", \"answer\": \"\"}, {\"name\":\"description\", \"answer\": \"\"}, {\"name\":\"price\", \"answer\": \"\"}, {\"name\":\"category\", \"answer\": \"\"}]}, {\"function\":\"Edit Product Details\", \"parameter\": [{\"name\":\"product_id\", \"answer\": \"\"}, {\"name\":\"product_name\", \"answer\": \"\"}, {\"name\":\"description\", \"answer\": \"\"}, {\"name\":\"price\", \"answer\": \"\"}, {\"name\":\"category\", \"answer\": \"\"}]}, {\"function\":\"Delete Product\", \"parameter\": [{\"name\":\"product_id\", \"answer\": \"\"}]}]}, {\"page\":\"Order Management\", \"function\":[{\"function\":\"View All Orders\", \"parameter\":[]}, {\"function\":\"Add New Order\", \"parameter\": [{\"name\":\"customer_id\", \"answer\": \"\"}, {\"name\":\"products\", \"answer\": \"\"}, {\"name\":\"shipping_address\", \"answer\": \"\"}]}, {\"function\":\"Edit Order Details\", \"parameter\": [{\"name\":\"order_id\", \"answer\": \"\"}, {\"name\":\"customer_id\", \"answer\": \"\"}, {\"name\":\"products\", \"answer\": \"\"}, {\"name\":\"shipping_address\", \"answer\": \"\"}]}, {\"function\":\"Delete Order\", \"parameter\": [{\"name\":\"order_id\", \"answer\": \"\"}]}]}, {\"page\":\"Analytics\", \"function\":[{\"function\":\"Generate Sales Report\", \"parameter\":[]}, {\"function\":\"Product Performance Analysis\", \"parameter\":[]}]}] ```", "14": "[{\"page\": \"HelloWorld\", \"function\": [{\"function\": \"DisplayText\", \"parameter\": [{\"name\": \"test_url\", \"answer\": \"http://localhost:8000/\"}, ]}, {\"function\": \"BasicStyling\", \"parameter\": [{\"name\": \"test_url\", \"answer\": \"http://localhost:8000/\"}, ]}, {\"function\": \"PageTitle\", \"parameter\": [{\"name\": \"test_url\", \"answer\": \"http://localhost:8000/\"}, ]}, {\"function\": \"MetaTags\", \"parameter\": [{\"name\": \"test_url\", \"answer\": \"http://localhost:8000/\"}, ]}]}]", "15": [{"page": "Home", "function": [{"function": "Button to 'HelloWorld' page", "parameter": [{"name": "test_url", "answer": "http://localhost:8000/hello-world"}]}]}, {"page": "HelloWorld", "function": [{"function": "Display 'HelloWorld' message", "parameter": []}]}], "16": [{"page": "Input File Validation", "function": [{"function": "CheckFileExistence", "parameter": [{"name": "entry", "answer": "page1.py"}, {"name": "error_message", "answer": "File 'page1.py' not found."}]}, {"function": "ValidateHeaders", "parameter": [{"name": "entry", "answer": "page1.py"}, {"name": "error_message", "answer": "Missing or incorrect headers in page1.py."}]}, {"function": "ValidateNullValue", "parameter": [{"name": "entry", "answer": "page1.py"}, {"name": "error_message", "answer": "Null values found in expected data columns of page1.py."}]}, {"function": "ValidateTimeColumn", "parameter": [{"name": "entry", "answer": "page1.py"}, {"name": "error_message", "answer": "Invalid time format in page1.py."}]}, {"function": "ValidateDataIntegrity", "parameter": [{"name": "entry", "answer": "page1.py"}, {"name": "error_message", "answer": "Weekday data inconsistency detected in page1.py."}]}]}, {"page": "Data Transformation and File Output", "function": [{"function": "EmptyFileRun", "parameter": [{"name": "entry", "answer": "None"}]}, {"function": "RunProject", "parameter": [{"name": "entry", "answer": "None"}]}, {"function": "OutputFileCheck", "parameter": []}]}], "18": "[{\"page\": \"Main Menu\", \"function\": [{\"function\": \"Welcome Message\", \"parameter\": [{\"name\": \"expected_output\", \"answer\": \"Welcome to the Text Adventure Game! Select a option to begin.\"}]}, {\"function\": \"Help in Main Menu\", \"parameter\": [{\"name\": \"help_in_main_menu_command\", \"answer\": 2}, {\"name\": \"expected_output\", \"answer\": \"Available Options:\\\\n1. Start Game\\\\n2. Help\\\\n3. Exit\"},]}, {\"function\": \"Wrong Selection Check\", \"parameter\": [{\"name\": \"expected_output\", \"answer\": \"Invalid selection. Please choose a valid option.\"}]}, {\"function\": \"Start Game\", \"parameter\": [{\"name\": \"start_game_command\", \"answer\": 1}, {\"name\": \"expected_output\", \"answer\": \"You find yourself at a crossroad. Paths lead north, south, east, and west.\"}]}]}, {\"page\": \"Game\", \"function\": [{\"function\": \"Display Help\", \"parameter\": [{\"name\": \"help_in_game\", \"answer\": \"? \", \"expected_output\": \"Available commands: \\\\nlook,\\\\nmove <direction>\\\\nexamine.\\\\ngo \\\\ngive\\\\npick\"}]}, {\"function\": \"Look Around\", \"parameter\": [{\"name\": \"expected_output\", \"answer\": \"You find yourself at a crossroad. Paths lead north, south, east, and west.\"}]}, {\"function\": \"Move Player\", \"parameter\": [{\"name\":  \"direction\", \"answer\": \"north \", \"desired_direction\": \"south\"}, {\"name\": \"expected_output\", \"answer\": \"Traveling south...\"}]}, {\"function\": \"Move Back\", \"parameter\": [{\"name\": \"expected_output\", \"answer\": \"\"}]}, {\"function\": \"Check Inventory 1\", \"parameter\": [{\"name\": \"check_inventory_command\", \"answer\": \"inventory\", \"expected_output\": \"Your inventory is empty.\"}]}, {\"function\": \"Pick Item\", \"parameter\": [{\"name\": \"directions\", \"answer\": \"bedroom, desk\", \"expected_output\": \"You picked up a key from the desk.\"}]}, {\"function\": \"Check Inventory 2\", \"parameter\": [{\"name\": \"check_inventory_command\", \"answer\": \"inventory\", \"expected_output\": \"Your inventory contains: key.\"}]}, {\"function\": \"Win the Game\", \"parameter\": [{\"name\": \"directions\", \"answer\": \"forest, village, castle \", \"expected_output\": \"Congratulations! You have won the game!\"}]}]},  {\"page\": \"Main Menu 2\", \"function\": [{\"function\": \"Exit Game\", \"parameter\": [{\"name\": \"exit_command\", \"answer\": 3}, {\"name\": \"expected_output\", \"answer\": \"Goodbye! Thank you for playing.\"}]}]}]", "19": [{"page": "Batch Program", "function": [{"function": "CheckFileExistence", "parameter": [{"name": "entry", "answer": "user_interface.py"}, {"name": "error_message", "answer": "File not found"}]}, {"function": "ValidateHeaders", "parameter": [{"name": "entry", "answer": "user_interface.py"}, {"name": "error_message", "answer": "Missing headers in file"}]}, {"function": "ValidateEmptyFile", "parameter": [{"name": "entry", "answer": "user_interface.py"}, {"name": "error_message", "answer": "File is empty"}]}, {"function": "ValidateTimeColumn", "parameter": [{"name": "entry", "answer": "user_interface.py"}, {"name": "error_message", "answer": "Invalid date format in file"}]}, {"function": "ValidateNullValue", "parameter": [{"name": "entry", "answer": "user_interface.py"}, {"name": "error_message", "answer": "Missing values in file"}]}, {"function": "RunProject1", "parameter": [{"name": "entry", "answer": "\"user_interface.py\" "}, {"name": "image_name", "answer": "\"output_image.png\""}]}, {"function": "RunProject2", "parameter": [{"name": "entry", "answer": "analysis_visualization.py"}, {"name": "image_name", "answer": "\"matplotlib_plot.png\""}]}]}], "20": [{"page": "Home", "function": [{"function": "Display Blog Posts", "parameter": [{"name": "post_item_class_name", "answer": "post-item"}, {"name": "blog_title_text", "answer": "Blog Title"}]}, {"function": "Show Categories List", "parameter": [{"name": "category_list_xpath", "answer": "//ul[@class='category-list']"}, {"name": "category_link_text", "answer": "Categories"}, {"name": "category_item_class_name", "answer": "post-category"}]}, {"function": "Display Search Form", "parameter": [{"name": "search_form_id", "answer": "search-form"}, {"name": "search_button_text", "answer": "Search"}]}]}, {"page": "Blog Post", "function": [{"function": "Display Blog Post Content", "parameter": []}, {"function": "Show Related Posts", "parameter": [{"name": "related_post_xpath", "answer": "//div[@class='related-posts']"}, {"name": "next_button_text", "answer": "Next"}]}]}, {"page": "Category Archive", "function": [{"function": "Display Category Blog Posts", "parameter": [{"name": "category_archive_page_xpath", "answer": "//div[@class='category-archive']"}, {"name": "category_title_text", "answer": "Blog Post Title"}]}, {"function": "Show Pagination Links", "parameter": [{"name": "pagination_link_class_name", "answer": "page-link"}]}]}, {"page": "Author Archive", "function": [{"function": "Display Author Bio", "parameter": []}, {"function": "Show Author Posts", "parameter": [{"name": "author_posts_xpath", "answer": "//div[@class='author-posts']"}]}]}, {"page": "Archive", "function": [{"function": "Date Filter", "parameter": [{"name": "date_filter_class_name", "answer": "blog-archive-filter"}, {"name": "archived_posts_xpath", "answer": "//div[@class='blog-post']"}]}]}, {"page": "About", "function": [{"function": "Display Author Information", "parameter": [{"name": "about_link_text", "answer": "About Us"}, {"name": "expected_text", "answer": "This is a test description for the about page."}]}]}]}